jupyterprobe/__init__.py
jupyterprobe/config.py
jupyterprobe/gpu_utils.py
jupyterprobe/jupyterprobe.py
jupyterprobe/memory_utils.py
jupyterprobe/plainUI.py
jupyterprobe/process_utils.py
jupyterprobe/register_utils.py
jupyterprobe/richUI.py
jupyter_probe-0.1.4.dist-info/LICENSE
jupyter_probe-0.1.4.dist-info/METADATA
jupyter_probe-0.1.4.dist-info/WHEEL
jupyter_probe-0.1.4.dist-info/top_level.txt
jupyter_probe-0.1.4.dist-info/RECORD
